aniso8601/__init__.py
aniso8601/compat.py
aniso8601/date.py
aniso8601/decimalfraction.py
aniso8601/duration.py
aniso8601/exceptions.py
aniso8601/interval.py
aniso8601/resolution.py
aniso8601/time.py
aniso8601/timezone.py
aniso8601/utcoffset.py
aniso8601/builders/__init__.py
aniso8601/builders/python.py
aniso8601/builders/tests/__init__.py
aniso8601/builders/tests/test_init.py
aniso8601/builders/tests/test_python.py
aniso8601/tests/__init__.py
aniso8601/tests/compat.py
aniso8601/tests/test_compat.py
aniso8601/tests/test_date.py
aniso8601/tests/test_decimalfraction.py
aniso8601/tests/test_duration.py
aniso8601/tests/test_init.py
aniso8601/tests/test_interval.py
aniso8601/tests/test_time.py
aniso8601/tests/test_timezone.py
aniso8601/tests/test_utcoffset.py
aniso8601-9.0.0.dist-info/LICENSE
aniso8601-9.0.0.dist-info/METADATA
aniso8601-9.0.0.dist-info/WHEEL
aniso8601-9.0.0.dist-info/top_level.txt
aniso8601-9.0.0.dist-info/RECORD
