Metadata-Version: 2.1
Name: aniso8601
Version: 9.0.0
Summary: A library for parsing ISO 8601 strings.
Home-page: https://bitbucket.org/nielsenb/aniso8601
Author: Brandon Nielsen
Author-email: nielsenb@jetfuse.net
License: UNKNOWN
Project-URL: Documentation, https://aniso8601.readthedocs.io/
Project-URL: Source, https://bitbucket.org/nielsenb/aniso8601
Project-URL: Tracker, https://bitbucket.org/nielsenb/aniso8601/issues
Keywords: iso8601 parser
Platform: UNKNOWN
Classifier: Development Status :: 5 - Production/Stable
Classifier: Intended Audience :: Developers
Classifier: License :: OSI Approved :: BSD License
Classifier: Operating System :: OS Independent
Classifier: Programming Language :: Python
Classifier: Programming Language :: Python :: 2
Classifier: Programming Language :: Python :: 2.7
Classifier: Programming Language :: Python :: 3
Classifier: Programming Language :: Python :: 3.4
Classifier: Programming Language :: Python :: 3.5
Classifier: Programming Language :: Python :: 3.6
Classifier: Programming Language :: Python :: 3.7
Classifier: Programming Language :: Python :: 3.8
Classifier: Programming Language :: Python :: 3.9
Classifier: Topic :: Software Development :: Libraries :: Python Modules
